{
	"amakihi" : [
		{
			"ninoxe" : {
				"martinet" : "2015-12-8",
				"loriquet" : "2080-10-14",
				"pintade" : [ 79, "moucherolle" ]
			},
			"rouloul" : [
				{
					"coryllis" : [ "huitrier", 47 ],
					"grue" : "1986-6-28"
				}, 
				{
					"rouloul" : 29
				}
			]
		}, 
		19
	],
	"nestor" : {
		"linotte" : "choucas",
		"microtyran" : {
			"pseudosittine" : [ 66, 49 ],
			"argus" : "gorfou",
			"harfang" : [ "cordonnoir", "faucon" ]
		}
	},
	"conophage" : "perruche"
}

{
	"apalis" : [ "ara" ]
}

{
	"araponga" : "hautdechausses",
	"malcoha" : "miros",
	"bengali" : [ "drome", "iora" ]
}

{
	"bernache" : [
		{
			"courvite" : "2094-9-26",
			"prion" : [ 68 ]
		}
	],
	"taurillon" : {
		"martinchasseur" : "piaye",
		"doradite" : 70
	}
}

{
	"alcyon" : 45
}

{
	"upucerthie" : 88,
	"ara" : 33
}

{
	"barbican" : [
		{
			"lagopede" : [ "1943-10-27" ],
			"amarante" : 99
		}
	]
}

{
	"noddi" : "tectec"
}

{
	"eider" : {
		"tangara" : "grosbec",
		"aigrette" : "trembleur"
	},
	"poule" : {
		"barite" : "2058-6-22",
		"acanthize" : "upucerthie",
		"motmot" : "upucerthie",
		"touraco" : [ "colibri", "2097-4-20", 37 ]
	}
}

{
	"palette" : {
		"piquebaie" : 53
	},
	"veuve" : 17
}

{
	"phodile" : [
		"dinornis", 
		{
			"mouette" : "tourco",
			"microgoura" : "brillant",
			"eulophe" : {
				"eulophe" : [ "sittine", "guitguit" ],
				"rouloul" : [ 3, "becenarc" ]
			}
		}
	],
	"palette" : "corbeau"
}

{
	"perruche" : [ "busard", "messager" ],
	"sirli" : "kookaburra",
	"perroquethibou" : 31
}

{
	"nandou" : [
		{
			"grimpereau" : [ 68 ]
		}
	],
	"cacholote" : {
		"chionis" : [ "picotelle" ]
	}
}

{
	"founingo" : {
		"caurale" : {
			"carnifex" : 100,
			"francolin" : [ "goeland", "rolle" ],
			"podarge" : "autour"
		},
		"minivet" : "oreochare",
		"sittine" : [
			{
				"sirli" : "ombrette"
			}, 
			"labbe"
		]
	},
	"trogon" : {
		"todier" : {
			"accenteur" : [ "2022-9-26", "etourneau" ],
			"caurale" : "doradite"
		},
		"harelde" : {
			"araguira" : "pomatostome",
			"pione" : 12
		}
	},
	"marabout" : {
		"annumbi" : {
			"piaye" : [ "2021-4-28", "acanthize" ]
		},
		"actinodure" : [
			"cassican", 
			"flamant"
		]
	}
}

{
	"pteronette" : [ "coucoupe" ],
	"akalat" : [ "2029-9-27" ]
}

{
	"erione" : 33
}

{
	"coulicou" : "callonette",
	"heliange" : [ "2024-10-20" ]
}

{
	"poule" : "barite"
}

{
	"garrot" : {
		"ibis" : 16,
		"microtyran" : "choucas"
	},
	"casiorne" : {
		"astrildcaille" : [ "1984-7-4", 55 ]
	},
	"tuittuit" : {
		"faisan" : "becencheville",
		"alcippe" : "gymnorhine"
	}
}

{
	"vireo" : {
		"coq" : "nandou",
		"autruche" : "apalis"
	}
}

{
	"harle" : "araguira"
}

{
	"gypaete" : "phodile",
	"psittricha" : "molothre",
	"vautour" : 35
}

{
	"porteeventail" : "etourneau"
}

{
	"loddigesie" : {
		"ganga" : "ortalide",
		"craterope" : "1934-6-14"
	}
}

{
	"pipit" : "2007-9-25"
}

{
	"akalat" : [ "2003-4-11" ],
	"gypaete" : [ "pseudosittine" ]
}

{
	"avocette" : {
		"pygargue" : "2004-8-11"
	},
	"pivert" : {
		"busautour" : {
			"zosterops" : "1943-11-20"
		},
		"syrrhapte" : {
			"crick" : "2072-2-23",
			"psittacule" : "todier"
		}
	}
}

{
	"grallaire" : "androphobe",
	"ani" : {
		"barite" : "amytis",
		"fou" : "2082-8-12",
		"busard" : 36
	},
	"gaucho" : {
		"gymnorhine" : "achetopse",
		"cygne" : "bateleur"
	}
}

{
	"cacholote" : "dindon",
	"timalie" : "erismature"
}

{
	"inca" : "1954-9-15"
}

{
	"pigeon" : "pedionome"
}

{
	"kapako" : [
		"roselin", 
		23
	],
	"palicour" : {
		"tyran" : {
			"touraco" : 80,
			"hautdechausses" : "echenilleur"
		},
		"troglodyte" : {
			"nestor" : [ "2004-5-19", "atrichorne" ],
			"coulicou" : [ "psittricha", "loddigesie" ]
		},
		"merion" : [
			61, 
			{
				"condor" : "cassican",
				"sarcoramphe" : "bulbul",
				"batara" : "2034-12-28"
			}
		]
	}
}

{
	"alethe" : "miros",
	"hibou" : "2080-1-27",
	"flamant" : "2022-11-24"
}

{
	"bengali" : {
		"otidiphaps" : {
			"iora" : "guepier",
			"cisticole" : [ "colin", 25 ],
			"corneille" : "hocco"
		},
		"dicee" : {
			"manchot" : [ "pseudolangrayen", "amblyospize" ]
		},
		"platyrhynque" : {
			"faucon" : "coracine"
		}
	},
	"vanga" : 75,
	"sirli" : {
		"crick" : [
			{
				"meliphage" : 49
			}, 
			{
				"tourterelle" : 33,
				"canaroie" : "2044-2-19",
				"tantale" : [ "canaroie", "sapayoa" ]
			}
		],
		"queuegrise" : "1978-12-8"
	}
}

{
	"choucas" : "1963-1-26",
	"corythopis" : "2044-12-23",
	"ariane" : 47
}

{
	"oceanite" : {
		"sarcoramphe" : {
			"apalis" : "2039-6-21"
		}
	}
}

{
	"sittelle" : {
		"carpophage" : 71,
		"merganette" : "2039-9-2",
		"chevechette" : 14
	},
	"spreo" : [
		{
			"coscoroba" : [ "coquette", "calobate" ],
			"kaka" : "rougequeue"
		}, 
		{
			"stercoraire" : 93,
			"puffin" : 29,
			"ariane" : 54
		}
	],
	"gralline" : {
		"couturiere" : "guepier"
	}
}

{
	"myrmidon" : [
		{
			"lerva" : 11
		}
	],
	"papangue" : {
		"heteronette" : [ "1913-9-10" ],
		"etourneau" : [ 7 ]
	}
}

{
	"papegeai" : [ "sylphe", "milan" ],
	"echasse" : "turnix",
	"penelope" : [ "2025-12-11", "1939-8-18" ]
}

{
	"pione" : "guillemot",
	"mesangeai" : 44,
	"grimpereau" : "circaete",
	"durbec" : "1925-9-13"
}

{
	"cassican" : {
		"oreochare" : "arlequin",
		"harpie" : "bouvreuil",
		"haliete" : "pluvian"
	},
	"uraete" : {
		"saphir" : [ "huppe", 71, 96 ]
	},
	"faucon" : {
		"autruche" : "baza"
	},
	"tichodrome" : {
		"caurale" : [ "rolle", "antriade", "metallure" ],
		"rousserolle" : "emeu"
	}
}

{
	"lessonie" : [
		{
			"faisan" : "perroquethibou"
		}
	]
}

{
	"gymnorhine" : [
		{
			"martinet" : "1963-12-7"
		}
	],
	"cacholote" : "myrmidon"
}

{
	"grimpereau" : {
		"phapitreron" : [
			{
				"motmot" : "upucerthie"
			}
		],
		"ouette" : "colombar"
	}
}

{
	"manakin" : "couturiere",
	"engoulevent" : 96
}

{
	"ortalide" : {
		"tectec" : {
			"outarde" : "cisticole"
		},
		"manakin" : [
			{
				"papegeai" : [ "2027-11-2" ],
				"ketoupa" : [ "talegalle" ]
			}
		]
	},
	"megasittine" : {
		"pygargue" : [
			{
				"aigle" : "2011-1-2"
			}
		],
		"pioui" : [
			{
				"bateleur" : "ombrette"
			}
		]
	}
}

{
	"alethe" : {
		"pepoaza" : "elanion"
	},
	"phodile" : [
		"siffleurs", 
		{
			"todier" : {
				"emeu" : 80,
				"zoster" : "maubeche",
				"calobate" : [ 28, "astrild", "1916-11-22" ]
			},
			"martinet" : "sittelle",
			"autour" : "milan",
			"xenique" : {
				"cassique" : "sterne",
				"mesangeai" : 66,
				"breve" : 81
			}
		}, 
		"1941-10-14"
	]
}

{
	"acanthize" : [
		{
			"alouette" : [ "toucan" ]
		}
	],
	"gerygones" : [
		{
			"whakapapa" : [ "1973-11-11" ],
			"oie" : "chevalier"
		}
	]
}

{
	"dormilon" : {
		"gaucho" : [
			{
				"becassine" : [ "tectec" ],
				"spreo" : [ "1910-2-28" ]
			}
		]
	},
	"glareole" : {
		"cotinga" : {
			"nicobar" : "1921-7-8",
			"conure" : "stercoraire"
		}
	}
}

{
	"mesange" : [ "grebifoulque" ],
	"cheveche" : [ "2009-6-17" ]
}

{
	"becenarc" : "dryade",
	"sittine" : "portelance"
}

{
	"coquette" : "circaete"
}

{
	"eperonnier" : {
		"toxoramphes" : "traquet"
	},
	"organiste" : "picumne",
	"tocro" : {
		"eurylaime" : [
			{
				"lophophore" : "mesange",
				"cassique" : [ "1961-7-4", 19 ],
				"colvert" : "2082-12-26"
			}, 
			{
				"guillemot" : 69,
				"serpentaire" : 23
			}
		],
		"grisin" : {
			"grebifoulque" : "amarante"
		}
	}
}

{
	"bathmocerque" : [
		{
			"gymnorhine" : {
				"todirostre" : [ "ouette", "2026-9-28" ]
			}
		}, 
		{
			"queuegrise" : {
				"serin" : "rolle"
			},
			"akalat" : {
				"gypaete" : 5
			},
			"sarcelle" : {
				"torqueole" : "busard",
				"cagou" : "2031-5-27",
				"carnifex" : "pteronette"
			}
		}
	]
}

{
	"balbuzard" : "sentinelle"
}

{
	"esclave" : [
		{
			"mango" : [
				"mesite"
			]
		}
	],
	"erismature" : {
		"grallaire" : [
			{
				"lophophore" : "pione",
				"torqueole" : "1956-4-22"
			}
		],
		"hibou" : "tourco"
	}
}

{
	"calopsitte" : {
		"sirli" : "anomalospize",
		"pigeon" : [
			{
				"heron" : "1964-12-23",
				"bambusicole" : [ 48 ]
			}
		]
	}
}

{
	"rhipidure" : "1989-7-6"
}

{
	"hokki" : {
		"chevalier" : 31
	}
}

{
	"amblyospize" : {
		"loddigesie" : {
			"alecto" : [ "langrayen" ]
		},
		"batara" : {
			"batara" : [ 19 ]
		}
	},
	"faucon" : {
		"guacharo" : "palicour"
	}
}

{
	"kaka" : [
		"achetopse", 
		"nicobar", 
		{
			"martinpecheur" : "phodile",
			"piaye" : 80,
			"amarante" : "bergeronnette",
			"otidiphaps" : "2046-7-25"
		}
	],
	"mergule" : {
		"microgoura" : "1904-1-23",
		"serpentaire" : 66,
		"glareole" : "harelde"
	},
	"whakapapa" : {
		"tityre" : "megapode",
		"chouette" : "1963-6-1",
		"foudi" : 54,
		"bulbul" : "ninoxe"
	}
}

{
	"amblyospize" : "beccroise"
}

{
	"lessonie" : "psittricha",
	"guillemot" : "ortalide"
}

{
	"cincle" : "plongeon",
	"mango" : [ 74, "1997-7-5" ],
	"craterope" : "anomalospize"
}

{
	"ombrette" : 32,
	"tariette" : [ "cacatoes", "moinelette", 97 ],
	"calobate" : "caique",
	"stercoraire" : 28
}

{
	"coliou" : {
		"gallinule" : "1908-1-25"
	},
	"grive" : {
		"becassine" : [ "1933-8-3", "cinclosome" ]
	}
}

{
	"colombar" : {
		"barbican" : "aigrette"
	},
	"savacou" : {
		"balbuzard" : [
			{
				"eider" : "jacamar"
			}, 
			{
				"oie" : [ "barbu", "palette" ]
			}
		],
		"zoster" : 74
	}
}

{
	"grandduc" : "flamant",
	"couturiere" : "conophage"
}

{
	"torcol" : "gallinule",
	"corbicrave" : {
		"bruant" : 88,
		"micropsitte" : "spreo",
		"otidiphaps" : [ "pseudolangrayen", "beaumarquet", "moucherolle" ]
	},
	"epervier" : {
		"urubu" : [ "loriquet", "1989-2-2", "2085-3-25" ]
	},
	"grosbec" : {
		"linotte" : "1942-5-10",
		"tournepierre" : "xenoperdrix"
	}
}

{
	"plongeon" : {
		"uraete" : "sclerure"
	}
}

{
	"jacamar" : {
		"manchot" : {
			"pie" : [ "mouette" ],
			"tuittuit" : "2041-6-18"
		},
		"bergeronnette" : {
			"queuedegaze" : [ "hulotte" ],
			"ptilope" : "2026-8-13"
		}
	}
}

{
	"atrichorne" : {
		"taurillon" : "gerygones",
		"agami" : "sittelle",
		"piprite" : "organiste",
		"rougegorge" : 85
	},
	"martinpecheur" : {
		"pipromorphe" : "tetedefeu",
		"pigeon" : 26
	},
	"galloperdrix" : {
		"autour" : 8
	}
}

{
	"coua" : [ 74, "pedionome", "2012-1-12" ]
}

{
	"circaete" : "2098-12-21",
	"bondree" : [ "cagou", 48 ]
}

{
	"aracari" : "ganga",
	"cacatoes" : {
		"leipoa" : "ariane",
		"autour" : 75
	}
}

{
	"picumne" : {
		"eclectus" : [ "2049-4-8", 21 ],
		"erione" : "2006-5-25"
	}
}

{
	"corbicrave" : {
		"guitguit" : {
			"foulque" : [ 2, "2097-3-11", "2086-12-27" ],
			"pluvianelle" : 56
		},
		"coq" : {
			"poule" : "sphecothere"
		},
		"apotre" : {
			"circaete" : "petrel",
			"auripare" : "dryade",
			"guacharo" : "cygne"
		}
	},
	"paruline" : {
		"bernache" : "1908-11-11",
		"crabier" : [
			{
				"guepier" : 8,
				"republicain" : 50,
				"sericorne" : "piquebaie"
			}, 
			{
				"sentinelle" : "2083-8-12",
				"dicneme" : "busautour",
				"bateleur" : "1957-6-23",
				"gobemouche" : "amytis"
			}, 
			84
		],
		"chouettepecheuse" : [
			{
				"circaete" : "cacatoes",
				"mesange" : 99
			}, 
			"2067-9-28", 
			{
				"merle" : "1998-12-14",
				"cigogne" : "canaroie"
			}
		]
	}
}

{
	"whakapapa" : {
		"geocoucou" : "achetopse"
	}
}

{
	"oiearmee" : {
		"langrayen" : "1946-7-4"
	}
}

{
	"achetopse" : [ 25, "1907-10-7" ]
}

{
	"nestor" : [ 24 ]
}

{
	"haliete" : {
		"gallicolombe" : {
			"caurale" : "1977-6-1",
			"sapayoa" : "linotte"
		},
		"coliou" : [
			{
				"grebe" : "amblyospize"
			}, 
			{
				"moineau" : "2058-6-1"
			}
		]
	}
}

{
	"noddi" : [
		"corbeau", 
		{
			"miros" : [
				"lophophore", 
				{
					"canaroie" : "2052-1-17",
					"maubeche" : "gymnogene",
					"founingo" : [ "echenilleur", "meliphage" ]
				}
			],
			"guitguit" : "pipit"
		}
	]
}

{
	"chilia" : {
		"promerops" : 75
	},
	"mesange" : {
		"egothele" : [ "talegalle", "dindon" ],
		"loriot" : "ibijau",
		"onore" : 1
	}
}

{
	"coliou" : {
		"crabier" : [ "savacou" ],
		"araponga" : [ 79 ]
	},
	"rossignol" : {
		"porteeventail" : "2078-2-23"
	}
}

{
	"fauconnet" : "otidiphaps",
	"balbuzard" : {
		"carpophage" : "etourneau",
		"tariette" : "2096-8-25",
		"megasittine" : "huia"
	}
}

{
	"irrisor" : {
		"alecto" : [
			"hautdechausses"
		],
		"circaete" : {
			"gymnorhine" : [ 89 ]
		}
	},
	"pitohui" : {
		"ophrysie" : [
			{
				"tetraophase" : "grimpereau"
			}
		],
		"cigogne" : [
			"1982-2-21"
		]
	}
}

{
	"jacamar" : "condor",
	"meliphage" : "2004-9-23",
	"mesange" : [ "1955-2-20", "canard", "vireo" ]
}

{
	"salangane" : 18
}

{
	"martinchasseur" : {
		"messager" : "amakihi",
		"attagis" : 90
	},
	"courol" : "2027-12-17"
}

{
	"nandou" : {
		"spreo" : {
			"sittine" : "foudi",
			"anserelle" : "grimpar",
			"coua" : [ "1912-5-7", 51, "2022-10-17" ]
		},
		"hulotte" : {
			"achetopse" : "2049-10-1"
		}
	},
	"ptilope" : {
		"onore" : {
			"jaseur" : 27,
			"barbion" : "thinocore"
		},
		"fuligule" : {
			"couturiere" : 42,
			"piauhau" : 98
		},
		"iora" : {
			"hemiprocne" : [ "ara", "2005-2-14", 50 ],
			"quetzal" : [ "agrobate", "albatros", 6 ],
			"dendrocygne" : [ 80, "ombrette", "grimpereau" ],
			"pedionome" : "2011-10-25"
		}
	},
	"lophophore" : "hautdechausses",
	"pipit" : 13
}

{
	"ibis" : {
		"mesange" : "xenique",
		"prinia" : "sclerure",
		"grallaire" : "1919-8-13"
	},
	"barbu" : {
		"alecto" : "myzomele",
		"veuve" : "kookaburra"
	},
	"quetzal" : [
		{
			"guitguit" : [ "basilorne", "2059-2-14" ],
			"maubeche" : [ "2060-11-22", "2086-9-10" ]
		}, 
		{
			"poule" : [ "1920-1-6", "phaeton" ]
		}
	]
}

{
	"picotelle" : {
		"eider" : "pie",
		"mesangeai" : {
			"caurale" : "fou",
			"ketoupa" : "penelope"
		}
	}
}

{
	"macareux" : [
		"avocette"
	]
}

{
	"inseparable" : 60,
	"rougegorge" : 51,
	"grallaire" : 29
}

{
	"fulmar" : {
		"coulicou" : {
			"attagis" : [ "1959-11-20", 27 ],
			"inseparable" : "anserelle",
			"glareole" : "tyranneau"
		},
		"syrrhapte" : [
			{
				"hemiprocne" : [ "megapode", "moineau" ],
				"fuligule" : "1915-6-1",
				"vireo" : 83
			}, 
			{
				"irrisor" : [ "2061-9-3", "2070-9-11" ],
				"rossignol" : [ "2017-8-14", "canard" ]
			}
		]
	},
	"stourne" : {
		"piauhau" : [
			"rousserolle", 
			{
				"ninoxe" : 95,
				"huitrier" : "calopsitte"
			}
		]
	}
}

{
	"calobate" : {
		"cagou" : 2,
		"indicateur" : {
			"eperonnier" : "colibri",
			"chevechette" : "arlequin"
		}
	},
	"pluvianelle" : {
		"erione" : [
			{
				"guepier" : "psittricha",
				"touraco" : [ "2005-10-7" ]
			}
		]
	}
}

{
	"picertie" : {
		"dicee" : [ "1925-4-18", "cacholote" ],
		"becasseau" : "1956-2-28"
	},
	"doradite" : {
		"psittricha" : [ "brassemer", "metallure" ],
		"pic" : "anomalospize",
		"guira" : "2025-7-1"
	},
	"organiste" : {
		"chilia" : "1923-1-22",
		"breve" : [ "piaye", "2041-12-14" ]
	}
}

{
	"gerygones" : {
		"sterne" : [ "tetras" ]
	}
}

{
	"phodile" : {
		"petitduc" : "moa",
		"corbeau" : [ "1907-12-17", "bouvreuil" ]
	},
	"meliphage" : {
		"allotrie" : "carpophage",
		"cardinal" : [ "2011-12-11", "geai" ]
	}
}

